LICENSE
README.md
setup.py
booze_tools.egg-info/PKG-INFO
booze_tools.egg-info/SOURCES.txt
booze_tools.egg-info/dependency_links.txt
booze_tools.egg-info/top_level.txt
boozetools/__init__.py
boozetools/__main__.py
boozetools/menagerie.py
boozetools/macroparse/__init__.py
boozetools/macroparse/compaction.py
boozetools/macroparse/compiler.py
boozetools/macroparse/expansion.py
boozetools/macroparse/grammar.py
boozetools/macroparse/interface.py
boozetools/macroparse/runtime.py
boozetools/parsing/__init__.py
boozetools/parsing/all_methods.py
boozetools/parsing/automata.py
boozetools/parsing/canonical.py
boozetools/parsing/context_free.py
boozetools/parsing/interface.py
boozetools/parsing/lalr.py
boozetools/parsing/lr0.py
boozetools/parsing/lr1.py
boozetools/parsing/miniparse.py
boozetools/parsing/shift_reduce.py
boozetools/parsing/general/__init__.py
boozetools/parsing/general/brute_force.py
boozetools/parsing/general/gss.py
boozetools/scanning/__init__.py
boozetools/scanning/charclass.py
boozetools/scanning/charset.py
boozetools/scanning/engine.py
boozetools/scanning/finite.py
boozetools/scanning/interface.py
boozetools/scanning/miniscan.py
boozetools/scanning/regular.py
boozetools/support/__init__.py
boozetools/support/failureprone.py
boozetools/support/foundation.py
boozetools/support/pretty.py
boozetools/support/symtab.py
boozetools/support/treelang.py
tests/test_bootstrap.py
tests/test_charclass.py
tests/test_context_free.py
tests/test_deterministic.py
tests/test_error_handling.py
tests/test_examples.py
tests/test_foundation.py
tests/test_generalized.py
tests/test_lalr.py
tests/test_miniparse.py
tests/test_miniscan.py
tests/test_non_lalr.py
tests/test_regular.py
tests/test_treelang.py