Metadata-Version: 2.1
Name: booze-tools
Version: 0.6.3
Summary: A panoply of tools for parsing, lexical analysis, and semantic processing
Home-page: https://github.com/kjosib/booze-tools
Author: Beth Kjos
Author-email: kjosib@gmail.com
Classifier: Programming Language :: Python :: 3.9
Classifier: License :: OSI Approved :: MIT License
Classifier: Operating System :: OS Independent
Classifier: Topic :: Software Development :: Compilers
Classifier: Development Status :: 3 - Alpha
License-File: LICENSE
